pymrm/__init__.py
pymrm/_version.py
pymrm/convect.py
pymrm/coupling.py
pymrm/grid.py
pymrm/helpers.py
pymrm/interpolate.py
pymrm/numjac.py
pymrm/operators.py
pymrm/solve.py
pymrm-2.2.20.dist-info/licenses/LICENSE
pymrm-2.2.20.dist-info/METADATA
pymrm-2.2.20.dist-info/WHEEL
pymrm-2.2.20.dist-info/top_level.txt
pymrm-2.2.20.dist-info/RECORD
