Metadata-Version: 2.4
Name: pymrm
Version: 2.2.20
Summary: Functions for multiphase reactor modeling
Author-email: "E.A.J.F. Peters" <e.a.j.f.peters@tue.nl>, "M. van Sint Annaland" <M.v.SintAnnaland@tue.nl>, "M. Galanti" <m.galanti@tue.nl>, "D.R. Rieder" <d.r.rieder@tue.nl>
Maintainer-email: "E.A.J.F. Peters" <e.a.j.f.peters@tue.nl>
License: MIT License
Project-URL: Homepage, https://multiscale-modelling-multiphase-flows.github.io/pymrm-book
Project-URL: Repository, https://github.com/multiscale-modelling-multiphase-flows/pymrm
Keywords: MRM,modeling,multiphase,diffusion,convection
Classifier: Development Status :: 4 - Beta
Classifier: Programming Language :: Python :: 3.10
Classifier: Programming Language :: Python :: 3.11
Classifier: Programming Language :: Python :: 3.12
Classifier: License :: OSI Approved :: MIT License
Classifier: Intended Audience :: Science/Research
Classifier: Topic :: Scientific/Engineering
Requires-Python: >=3.10
License-File: LICENSE
Requires-Dist: pip>=24.0
Requires-Dist: numpy>=1.26
Requires-Dist: scipy>=1.13
Requires-Dist: numba>=0.58
Requires-Dist: pandas>=2.2
Requires-Dist: matplotlib>=3.8
Requires-Dist: ipython>=8.20
Requires-Dist: ipykernel>=6.28
Requires-Dist: pytest>=8.3.4
Requires-Dist: pytest-cov
Requires-Dist: sphinx
Requires-Dist: sphinx_rtd_theme
Requires-Dist: nbclient
Requires-Dist: myst-parser
Dynamic: license-file
